tfs_client/__init__.py
tfs_client/http.py
tfs_client/util/__init__.py
tfs_client/util/postprocessing.py
tfs_client/util/cit_images/__init__.py
tfs_client/util/cit_images/cit_images.py
tfs_client-0.1.13.dist-info/METADATA
tfs_client-0.1.13.dist-info/WHEEL
tfs_client-0.1.13.dist-info/top_level.txt
tfs_client-0.1.13.dist-info/RECORD
