Metadata-Version: 2.1
Name: tfs-client
Version: 0.1.13
Summary: Tools to simplify access to TFServing via HTTP, specially for Moveread
Author-email: Marcel Claramunt <marcel@moveread.com>
Requires-Python: >=3.10
Requires-Dist: aiohttp
Requires-Dist: haskellian
Requires-Dist: pydantic
Requires-Dist: typing-extensions
